aaaaaaa_blursed.pth
blursed.py
blursed-0.0.2.dist-info/LICENSE
blursed-0.0.2.dist-info/METADATA
blursed-0.0.2.dist-info/WHEEL
blursed-0.0.2.dist-info/top_level.txt
blursed-0.0.2.dist-info/RECORD
