Metadata-Version: 2.1
Name: blursed
Version: 0.0.2
Summary: Just because you doesn't mean you should
Home-page: https://github.com/ckw017/blursed
Author: Chris K. W.
Author-email: chriskw.xyz@gmail.com
License: MIT
Platform: UNKNOWN
Classifier: License :: OSI Approved :: MIT License
Requires-Python: !=2.*,!=3.0.*,!=3.1.*,!=3.2.*,!=3.3.*,!=3.4.*
Requires-Dist: tokenize-rt
